{
    "title": "CSVAsset",
    "description": "Read a comma-separated values (csv) file into DataFrame.\n\nAlso supports optionally iterating or breaking of the file\ninto chunks.\n\nAdditional help can be found in the online docs for\n`IO Tools <https://pandas.pydata.org/pandas-docs/stable/user_guide/io.html>`_.\n\nParameters\n----------\nfilepath_or_buffer : str, path object or file-like object\n    Any valid string path is acceptable. The string could be a URL. Valid\n    URL schemes include http, ftp, s3, gs, and file. For file URLs, a host is\n    expected. A local file could be: file://localhost/path/to/table.csv.\n\n    If you want to pass in a path object, pandas accepts any ``os.PathLike``.\n\n    By file-like object, we refer to objects with a ``read()`` method, such as\n    a file handle (e.g. via builtin ``open`` function) or ``StringIO``.\nsep : str, default ','\n    Delimiter to use. If sep is None, the C engine cannot automatically detect\n    the separator, but the Python parsing engine can, meaning the latter will\n    be used and automatically detect the separator by Python's builtin sniffer\n    tool, ``csv.Sniffer``. In addition, separators longer than 1 character and\n    different from ``'\\s+'`` will be interpreted as regular expressions and\n    will also force the use of the Python parsing engine. Note that regex\n    delimiters are prone to ignoring quoted data. Regex example: ``'\\r\\t'``.\ndelimiter : str, default ``None``\n    Alias for sep.\nheader : int, list of int, default 'infer'\n    Row number(s) to use as the column names, and the start of the\n    data.  Default behavior is to infer the column names: if no names\n    are passed the behavior is identical to ``header=0`` and column\n    names are inferred from the first line of the file, if column\n    names are passed explicitly then the behavior is identical to\n    ``header=None``. Explicitly pass ``header=0`` to be able to\n    replace existing names. The header can be a list of integers that\n    specify row locations for a multi-index on the columns\n    e.g. [0,1,3]. Intervening rows that are not specified will be\n    skipped (e.g. 2 in this example is skipped). Note that this\n    parameter ignores commented lines and empty lines if\n    ``skip_blank_lines=True``, so ``header=0`` denotes the first line of\n    data rather than the first line of the file.\nnames : array-like, optional\n    List of column names to use. If the file contains a header row,\n    then you should explicitly pass ``header=0`` to override the column names.\n    Duplicates in this list are not allowed.\nindex_col : int, str, sequence of int / str, or False, default ``None``\n  Column(s) to use as the row labels of the ``DataFrame``, either given as\n  string name or column index. If a sequence of int / str is given, a\n  MultiIndex is used.\n\n  Note: ``index_col=False`` can be used to force pandas to *not* use the first\n  column as the index, e.g. when you have a malformed file with delimiters at\n  the end of each line.\nusecols : list-like or callable, optional\n    Return a subset of the columns. If list-like, all elements must either\n    be positional (i.e. integer indices into the document columns) or strings\n    that correspond to column names provided either by the user in `names` or\n    inferred from the document header row(s). For example, a valid list-like\n    `usecols` parameter would be ``[0, 1, 2]`` or ``['foo', 'bar', 'baz']``.\n    Element order is ignored, so ``usecols=[0, 1]`` is the same as ``[1, 0]``.\n    To instantiate a DataFrame from ``data`` with element order preserved use\n    ``pd.read_csv(data, usecols=['foo', 'bar'])[['foo', 'bar']]`` for columns\n    in ``['foo', 'bar']`` order or\n    ``pd.read_csv(data, usecols=['foo', 'bar'])[['bar', 'foo']]``\n    for ``['bar', 'foo']`` order.\n\n    If callable, the callable function will be evaluated against the column\n    names, returning names where the callable function evaluates to True. An\n    example of a valid callable argument would be ``lambda x: x.upper() in\n    ['AAA', 'BBB', 'DDD']``. Using this parameter results in much faster\n    parsing time and lower memory usage.\nsqueeze : bool, default False\n    If the parsed data only contains one column then return a Series.\nprefix : str, optional\n    Prefix to add to column numbers when no header, e.g. 'X' for X0, X1, ...\nmangle_dupe_cols : bool, default True\n    Duplicate columns will be specified as 'X', 'X.1', ...'X.N', rather than\n    'X'...'X'. Passing in False will cause data to be overwritten if there\n    are duplicate names in the columns.\ndtype : Type name or dict of column -> type, optional\n    Data type for data or columns. E.g. {'a': np.float64, 'b': np.int32,\n    'c': 'Int64'}\n    Use `str` or `object` together with suitable `na_values` settings\n    to preserve and not interpret dtype.\n    If converters are specified, they will be applied INSTEAD\n    of dtype conversion.\nengine : {'c', 'python'}, optional\n    Parser engine to use. The C engine is faster while the python engine is\n    currently more feature-complete.\nconverters : dict, optional\n    Dict of functions for converting values in certain columns. Keys can either\n    be integers or column labels.\ntrue_values : list, optional\n    Values to consider as True.\nfalse_values : list, optional\n    Values to consider as False.\nskipinitialspace : bool, default False\n    Skip spaces after delimiter.\nskiprows : list-like, int or callable, optional\n    Line numbers to skip (0-indexed) or number of lines to skip (int)\n    at the start of the file.\n\n    If callable, the callable function will be evaluated against the row\n    indices, returning True if the row should be skipped and False otherwise.\n    An example of a valid callable argument would be ``lambda x: x in [0, 2]``.\nskipfooter : int, default 0\n    Number of lines at bottom of file to skip (Unsupported with engine='c').\nnrows : int, optional\n    Number of rows of file to read. Useful for reading pieces of large files.\nna_values : scalar, str, list-like, or dict, optional\n    Additional strings to recognize as NA/NaN. If dict passed, specific\n    per-column NA values.  By default the following values are interpreted as\n    NaN: '', '#N/A', '#N/A N/A', '#NA', '-1.#IND', '-1.#QNAN', '-NaN', '-nan',\n    '1.#IND', '1.#QNAN', '<NA>', 'N/A', 'NA', 'NULL', 'NaN', 'n/a',\n    'nan', 'null'.\nkeep_default_na : bool, default True\n    Whether or not to include the default NaN values when parsing the data.\n    Depending on whether `na_values` is passed in, the behavior is as follows:\n\n    * If `keep_default_na` is True, and `na_values` are specified, `na_values`\n      is appended to the default NaN values used for parsing.\n    * If `keep_default_na` is True, and `na_values` are not specified, only\n      the default NaN values are used for parsing.\n    * If `keep_default_na` is False, and `na_values` are specified, only\n      the NaN values specified `na_values` are used for parsing.\n    * If `keep_default_na` is False, and `na_values` are not specified, no\n      strings will be parsed as NaN.\n\n    Note that if `na_filter` is passed in as False, the `keep_default_na` and\n    `na_values` parameters will be ignored.\nna_filter : bool, default True\n    Detect missing value markers (empty strings and the value of na_values). In\n    data without any NAs, passing na_filter=False can improve the performance\n    of reading a large file.\nverbose : bool, default False\n    Indicate number of NA values placed in non-numeric columns.\nskip_blank_lines : bool, default True\n    If True, skip over blank lines rather than interpreting as NaN values.\nparse_dates : bool or list of int or names or list of lists or dict, default False\n    The behavior is as follows:\n\n    * boolean. If True -> try parsing the index.\n    * list of int or names. e.g. If [1, 2, 3] -> try parsing columns 1, 2, 3\n      each as a separate date column.\n    * list of lists. e.g.  If [[1, 3]] -> combine columns 1 and 3 and parse as\n      a single date column.\n    * dict, e.g. {'foo' : [1, 3]} -> parse columns 1, 3 as date and call\n      result 'foo'\n\n    If a column or index cannot be represented as an array of datetimes,\n    say because of an unparsable value or a mixture of timezones, the column\n    or index will be returned unaltered as an object data type. For\n    non-standard datetime parsing, use ``pd.to_datetime`` after\n    ``pd.read_csv``. To parse an index or column with a mixture of timezones,\n    specify ``date_parser`` to be a partially-applied\n    :func:`pandas.to_datetime` with ``utc=True``. See\n    :ref:`io.csv.mixed_timezones` for more.\n\n    Note: A fast-path exists for iso8601-formatted dates.\ninfer_datetime_format : bool, default False\n    If True and `parse_dates` is enabled, pandas will attempt to infer the\n    format of the datetime strings in the columns, and if it can be inferred,\n    switch to a faster method of parsing them. In some cases this can increase\n    the parsing speed by 5-10x.\nkeep_date_col : bool, default False\n    If True and `parse_dates` specifies combining multiple columns then\n    keep the original columns.\ndate_parser : function, optional\n    Function to use for converting a sequence of string columns to an array of\n    datetime instances. The default uses ``dateutil.parser.parser`` to do the\n    conversion. Pandas will try to call `date_parser` in three different ways,\n    advancing to the next if an exception occurs: 1) Pass one or more arrays\n    (as defined by `parse_dates`) as arguments; 2) concatenate (row-wise) the\n    string values from the columns defined by `parse_dates` into a single array\n    and pass that; and 3) call `date_parser` once for each row using one or\n    more strings (corresponding to the columns defined by `parse_dates`) as\n    arguments.\ndayfirst : bool, default False\n    DD/MM format dates, international and European format.\ncache_dates : bool, default True\n    If True, use a cache of unique, converted dates to apply the datetime\n    conversion. May produce significant speed-up when parsing duplicate\n    date strings, especially ones with timezone offsets.\n\n    .. versionadded:: 0.25.0\niterator : bool, default False\n    Return TextFileReader object for iteration or getting chunks with\n    ``get_chunk()``.\n\n    .. versionchanged:: 1.2\n\n       ``TextFileReader`` is a context manager.\nchunksize : int, optional\n    Return TextFileReader object for iteration.\n    See the `IO Tools docs\n    <https://pandas.pydata.org/pandas-docs/stable/io.html#io-chunking>`_\n    for more information on ``iterator`` and ``chunksize``.\n\n    .. versionchanged:: 1.2\n\n       ``TextFileReader`` is a context manager.\ncompression : {'infer', 'gzip', 'bz2', 'zip', 'xz', None}, default 'infer'\n    For on-the-fly decompression of on-disk data. If 'infer' and\n    `filepath_or_buffer` is path-like, then detect compression from the\n    following extensions: '.gz', '.bz2', '.zip', or '.xz' (otherwise no\n    decompression). If using 'zip', the ZIP file must contain only one data\n    file to be read in. Set to None for no decompression.\nthousands : str, optional\n    Thousands separator.\ndecimal : str, default '.'\n    Character to recognize as decimal point (e.g. use ',' for European data).\nlineterminator : str (length 1), optional\n    Character to break file into lines. Only valid with C parser.\nquotechar : str (length 1), optional\n    The character used to denote the start and end of a quoted item. Quoted\n    items can include the delimiter and it will be ignored.\nquoting : int or csv.QUOTE_* instance, default 0\n    Control field quoting behavior per ``csv.QUOTE_*`` constants. Use one of\n    QUOTE_MINIMAL (0), QUOTE_ALL (1), QUOTE_NONNUMERIC (2) or QUOTE_NONE (3).\ndoublequote : bool, default ``True``\n   When quotechar is specified and quoting is not ``QUOTE_NONE``, indicate\n   whether or not to interpret two consecutive quotechar elements INSIDE a\n   field as a single ``quotechar`` element.\nescapechar : str (length 1), optional\n    One-character string used to escape other characters.\ncomment : str, optional\n    Indicates remainder of line should not be parsed. If found at the beginning\n    of a line, the line will be ignored altogether. This parameter must be a\n    single character. Like empty lines (as long as ``skip_blank_lines=True``),\n    fully commented lines are ignored by the parameter `header` but not by\n    `skiprows`. For example, if ``comment='#'``, parsing\n    ``#empty\\na,b,c\\n1,2,3`` with ``header=0`` will result in 'a,b,c' being\n    treated as the header.\nencoding : str, optional\n    Encoding to use for UTF when reading/writing (ex. 'utf-8'). `List of Python\n    standard encodings\n    <https://docs.python.org/3/library/codecs.html#standard-encodings>`_ .\n\n    .. versionchanged:: 1.2\n\n       When ``encoding`` is ``None``, ``errors=\"replace\"`` is passed to\n       ``open()``. Otherwise, ``errors=\"strict\"`` is passed to ``open()``.\n       This behavior was previously only the case for ``engine=\"python\"``.\n\n    .. versionchanged:: 1.3.0\n\n       ``encoding_errors`` is a new argument. ``encoding`` has no longer an\n       influence on how encoding errors are handled.\n\nencoding_errors : str, optional, default \"strict\"\n    How encoding errors are treated. `List of possible values\n    <https://docs.python.org/3/library/codecs.html#error-handlers>`_ .\n\n    .. versionadded:: 1.3.0\n\ndialect : str or csv.Dialect, optional\n    If provided, this parameter will override values (default or not) for the\n    following parameters: `delimiter`, `doublequote`, `escapechar`,\n    `skipinitialspace`, `quotechar`, and `quoting`. If it is necessary to\n    override values, a ParserWarning will be issued. See csv.Dialect\n    documentation for more details.\nerror_bad_lines : bool, default ``None``\n    Lines with too many fields (e.g. a csv line with too many commas) will by\n    default cause an exception to be raised, and no DataFrame will be returned.\n    If False, then these \"bad lines\" will be dropped from the DataFrame that is\n    returned.\n\n    .. deprecated:: 1.3.0\n       The ``on_bad_lines`` parameter should be used instead to specify behavior upon\n       encountering a bad line instead.\nwarn_bad_lines : bool, default ``None``\n    If error_bad_lines is False, and warn_bad_lines is True, a warning for each\n    \"bad line\" will be output.\n\n    .. deprecated:: 1.3.0\n       The ``on_bad_lines`` parameter should be used instead to specify behavior upon\n       encountering a bad line instead.\non_bad_lines : {'error', 'warn', 'skip'}, default 'error'\n    Specifies what to do upon encountering a bad line (a line with too many fields).\n    Allowed values are :\n\n        - 'error', raise an Exception when a bad line is encountered.\n        - 'warn', raise a warning when a bad line is encountered and skip that line.\n        - 'skip', skip bad lines without raising or warning when they are encountered.\n\n    .. versionadded:: 1.3.0\n\ndelim_whitespace : bool, default False\n    Specifies whether or not whitespace (e.g. ``' '`` or ``'    '``) will be\n    used as the sep. Equivalent to setting ``sep='\\s+'``. If this option\n    is set to True, nothing should be passed in for the ``delimiter``\n    parameter.\nlow_memory : bool, default True\n    Internally process the file in chunks, resulting in lower memory use\n    while parsing, but possibly mixed type inference.  To ensure no mixed\n    types either set False, or specify the type with the `dtype` parameter.\n    Note that the entire file is read into a single DataFrame regardless,\n    use the `chunksize` or `iterator` parameter to return the data in chunks.\n    (Only valid with C parser).\nmemory_map : bool, default False\n    If a filepath is provided for `filepath_or_buffer`, map the file object\n    directly onto memory and access the data directly from there. Using this\n    option can improve performance because there is no longer any I/O overhead.\nfloat_precision : str, optional\n    Specifies which converter the C engine should use for floating-point\n    values. The options are ``None`` or 'high' for the ordinary converter,\n    'legacy' for the original lower precision pandas converter, and\n    'round_trip' for the round-trip converter.\n\n    .. versionchanged:: 1.2\n\nstorage_options : dict, optional\n    Extra options that make sense for a particular storage connection, e.g.\n    host, port, username, password, etc. For HTTP(S) URLs the key-value pairs\n    are forwarded to ``urllib`` as header options. For other URLs (e.g.\n    starting with \"s3://\", and \"gcs://\") the key-value pairs are forwarded to\n    ``fsspec``. Please see ``fsspec`` and ``urllib`` for more details.\n\n    .. versionadded:: 1.2\n\nReturns\n-------\nDataFrame or TextParser\n    A comma-separated values (csv) file is returned as two-dimensional\n    data structure with labeled axes.\n\nSee Also\n--------\nDataFrame.to_csv : Write DataFrame to a comma-separated values (csv) file.\nread_csv : Read a comma-separated values (csv) file into DataFrame.\nread_fwf : Read a table of fixed-width formatted lines into DataFrame.\n\nExamples\n--------\n>>> pd.read_csv('data.csv')  # doctest: +SKIP",
    "type": "object",
    "properties": {
        "name": {
            "title": "Name",
            "type": "string"
        },
        "type": {
            "title": "Type",
            "default": "csv",
            "enum": [
                "csv"
            ],
            "type": "string"
        },
        "order_by": {
            "title": "Order By",
            "type": "array",
            "items": {
                "$ref": "#/definitions/BatchSorter"
            }
        },
        "base_directory": {
            "title": "Base Directory",
            "type": "string",
            "format": "path"
        },
        "regex": {
            "title": "Regex",
            "type": "string",
            "format": "regex"
        },
        "sep": {
            "title": "Sep",
            "default": "NO_DEFAULT"
        },
        "delimiter": {
            "title": "Delimiter"
        },
        "header": {
            "title": "Header",
            "default": "infer"
        },
        "names": {
            "title": "Names",
            "default": "NO_DEFAULT"
        },
        "index_col": {
            "title": "Index Col"
        },
        "usecols": {
            "title": "Usecols",
            "anyOf": [
                {
                    "type": "integer"
                },
                {
                    "type": "string"
                },
                {
                    "type": "array",
                    "items": {
                        "type": "integer"
                    }
                }
            ]
        },
        "squeeze": {
            "title": "Squeeze",
            "default": false
        },
        "prefix": {
            "title": "Prefix",
            "default": "NO_DEFAULT"
        },
        "mangle_dupe_cols": {
            "title": "Mangle Dupe Cols",
            "default": true
        },
        "dtype": {
            "title": "Dtype",
            "type": "object"
        },
        "engine": {
            "title": "Engine"
        },
        "converters": {
            "title": "Converters"
        },
        "true_values": {
            "title": "True Values"
        },
        "false_values": {
            "title": "False Values"
        },
        "skipinitialspace": {
            "title": "Skipinitialspace",
            "default": false
        },
        "skiprows": {
            "title": "Skiprows",
            "anyOf": [
                {
                    "type": "array",
                    "items": {
                        "type": "integer"
                    }
                },
                {
                    "type": "integer"
                }
            ]
        },
        "skipfooter": {
            "title": "Skipfooter",
            "default": 0
        },
        "nrows": {
            "title": "Nrows"
        },
        "na_values": {
            "title": "Na Values"
        },
        "keep_default_na": {
            "title": "Keep Default Na",
            "default": true
        },
        "na_filter": {
            "title": "Na Filter",
            "default": true
        },
        "verbose": {
            "title": "Verbose",
            "default": false
        },
        "skip_blank_lines": {
            "title": "Skip Blank Lines",
            "default": true
        },
        "parse_dates": {
            "title": "Parse Dates",
            "default": false
        },
        "infer_datetime_format": {
            "title": "Infer Datetime Format",
            "default": false
        },
        "keep_date_col": {
            "title": "Keep Date Col",
            "default": false
        },
        "date_parser": {
            "title": "Date Parser"
        },
        "dayfirst": {
            "title": "Dayfirst",
            "default": false
        },
        "cache_dates": {
            "title": "Cache Dates",
            "default": true
        },
        "iterator": {
            "title": "Iterator",
            "default": false
        },
        "chunksize": {
            "title": "Chunksize"
        },
        "compression": {
            "title": "Compression",
            "default": "infer"
        },
        "thousands": {
            "title": "Thousands"
        },
        "decimal": {
            "title": "Decimal",
            "default": ".",
            "type": "string"
        },
        "lineterminator": {
            "title": "Lineterminator"
        },
        "quotechar": {
            "title": "Quotechar",
            "default": "\""
        },
        "quoting": {
            "title": "Quoting",
            "default": 0
        },
        "doublequote": {
            "title": "Doublequote",
            "default": true
        },
        "escapechar": {
            "title": "Escapechar"
        },
        "comment": {
            "title": "Comment"
        },
        "encoding": {
            "title": "Encoding"
        },
        "encoding_errors": {
            "title": "Encoding Errors",
            "default": "strict",
            "type": "string"
        },
        "dialect": {
            "title": "Dialect",
            "type": "string"
        },
        "error_bad_lines": {
            "title": "Error Bad Lines"
        },
        "warn_bad_lines": {
            "title": "Warn Bad Lines"
        },
        "on_bad_lines": {
            "title": "On Bad Lines"
        },
        "delim_whitespace": {
            "title": "Delim Whitespace",
            "default": false
        },
        "low_memory": {
            "title": "Low Memory",
            "default": true
        },
        "memory_map": {
            "title": "Memory Map",
            "default": false
        },
        "float_precision": {
            "title": "Float Precision"
        },
        "storage_options": {
            "title": "Storage Options",
            "type": "object"
        }
    },
    "required": [
        "name",
        "base_directory",
        "regex"
    ],
    "additionalProperties": false,
    "definitions": {
        "BatchSorter": {
            "title": "BatchSorter",
            "type": "object",
            "properties": {
                "key": {
                    "title": "Key",
                    "type": "string"
                },
                "reverse": {
                    "title": "Reverse",
                    "default": false,
                    "type": "boolean"
                }
            },
            "required": [
                "key"
            ]
        }
    }
}
